hubmap_commons/21f293b0-globus-groups-new.json
hubmap_commons/21f293b0-globus-groups.json
hubmap_commons/21f293b0-process-user.json
hubmap_commons/S3_worker.py
hubmap_commons/activity.py
hubmap_commons/autherror.py
hubmap_commons/c4018852-globus-groups.json
hubmap_commons/c4018852-process-user.json
hubmap_commons/entity.py
hubmap_commons/exceptions.py
hubmap_commons/file_helper.py
hubmap_commons/globus_file_helper.py
hubmap_commons/hm_auth.py
hubmap_commons/hubmap-globus-roles.json
hubmap_commons/hubmap_const.py
hubmap_commons/hubmap_error.py
hubmap_commons/metadata.py
hubmap_commons/neo4j_connection.py
hubmap_commons/neo4j_driver.py
hubmap_commons/net_helper.py
hubmap_commons/properties.py
hubmap_commons/provenance.py
hubmap_commons/schema_tools.py
hubmap_commons/singleton_metaclass.py
hubmap_commons/string_helper.py
hubmap_commons/test_helper.py
hubmap_commons/test_ws.py
hubmap_commons/uuid_generator.py
hubmap_commons-2.1.22.dist-info/METADATA
hubmap_commons-2.1.22.dist-info/WHEEL
hubmap_commons-2.1.22.dist-info/top_level.txt
hubmap_commons-2.1.22.dist-info/RECORD
