Metadata-Version: 2.4
Name: hubmap-commons
Version: 2.1.22
Summary: The common utilities used by the HuMBAP web services
Home-page: https://github.com/hubmapconsortium/commons
Author: HuBMAP Consortium
Author-email: api-developers@hubmapconsortium.org
Classifier: Programming Language :: Python :: 3
Classifier: License :: OSI Approved :: MIT License
Classifier: Operating System :: OS Independent
Requires-Python: >=3.6
Requires-Dist: Flask>=2.1.3
Requires-Dist: jsonref==0.3.0
Requires-Dist: jsonschema>=3.2.0
Requires-Dist: neo4j>=4.2.1
Requires-Dist: pytz>=2021.1
Requires-Dist: property>=2.2
Requires-Dist: globus_sdk>=1.9.0
Requires-Dist: prov>=1.5.1
Requires-Dist: requests>=2.22.0
Requires-Dist: PyYAML>=5.3.1
Requires-Dist: boto3>=1.24.47
Dynamic: author
Dynamic: author-email
Dynamic: classifier
Dynamic: description
Dynamic: description-content-type
Dynamic: home-page
Dynamic: requires-dist
Dynamic: requires-python
Dynamic: summary
